{
  "case_id": 57,
  "is_depression": true,
  "disease_info": {
    "depression_level": "重度",
    "suicide_risk": 1,
    "symptoms_summary": ""
  },
  "case_info": {
    "basic_info": "67岁女性，退休小学语文教师，独居",
    "background": "丈夫3年前去世。近1年家属发现其“记性越来越差”，以为是“老年痴呆前兆”；近3个月因社区老年活动小组解散，情绪愈发低落，认知症状明显加重。",
    "check_results": "汉密尔顿抑郁量表（HAMD-17）评分24分（重度抑郁）。蒙特利尔认知评估量表（MoCA）评分24分（轻度认知损害，注意/执行功能分项得分仅4分）；MRI示轻度脑萎缩（与年龄相符）；APOE基因型为ε3/ε3（非阿尔茨海默病高风险基因型）；甲状腺功能正常。"
  },
  "dialogue_history": [
    "医生：您好，我是您的AI医生。感谢您今天来就诊。作为一位退休教师，生活节奏的变化和独居状态可能会带来一些挑战。能和我聊聊您最近的整体状态吗？",
    "患者：谢谢医生。最近确实感觉不太好，老伴走了三年了，以前还能去社区活动中心打发时间，现在连这个也没了。整天一个人在家，总觉得心里空落落的，做什么都提不起劲。",
    "医生：我能感受到您现在的孤独和失落。这种情绪低落的状态大概持续多久了呢？每天大部分时间都会这样吗？",
    "患者：从社区老年活动小组解散到现在差不多三个月了，感觉一天比一天难受。特别是早上醒来的时候，看着空荡荡的房间，眼泪就止不住地往下掉。一整天都打不起精神，连以前最喜欢的养花浇花都懒得动了。",
    "医生：听起来您失去了重要的社交支持，这确实会让人感到特别难过。除了情绪低落，您最近在睡眠和饮食方面有什么变化吗？",
    "患者：睡眠特别差，经常半夜两三点就醒了，然后就再也睡不着，躺在床上胡思乱想到天亮。吃饭也没什么胃口，女儿上周送来的饺子还在冰箱里冻着，有时候一天就喝点粥对付一下。",
    "医生：我注意到您提到睡眠和食欲都有明显变化。那么您平时喜欢做的事情，比如看看书或者和亲友联系，现在还愿意去做吗？",
    "患者：以前每天都要看报纸练字，现在连笔都拿不起来。女儿打电话来我也经常不想接，接了也不知道说什么好。家里堆了好多灰尘也不想打扫，就觉得整个人懒洋洋的，什么都不想做。",
    "医生：我理解这种对事物失去兴趣的感受。当您一个人在家时，会不会经常感到疲惫或精力不足？即使没有做什么特别消耗体力的事情。",
    "患者：是的，明明什么都没做却总觉得特别累。有时候想给自己泡杯茶，走到厨房就累得直喘气，只好又回去躺着。连最简单的家务活都觉得特别吃力，上个楼梯都要中途休息好几次。",
    "医生：这种精力不足的情况确实会让人感到困扰。您刚才提到经常半夜醒来胡思乱想，是否曾经出现过一些消极的念头，比如觉得活着很累之类的？",
    "患者：确实会想，要是能早点去陪老伴就好了。女儿外孙都有自己的生活，我一个人活着也是拖累他们。不过也就是想想而已，从来没打算真的做什么，毕竟还要看着外孙上大学呢。",
    "医生：感谢您愿意和我分享这些。当这些念头出现时，您通常是怎么应对的呢？会试着给女儿打个电话或者出门走走吗？",
    "患者：女儿工作忙，我不想总打扰她。有时候会翻翻相册看看老伴的照片，但越看心里越难受。最近连电视都不开了，就坐在窗边发呆，一坐就是大半天。",
    "医生：我能理解您不想给女儿添麻烦的心情。除了心理上的变化，您有没有注意到身体方面的一些改变？比如动作变得比平时慢，或者说话反应不如以前灵敏？",
    "患者：确实感觉动作慢了很多，女儿上次来还说我现在走路都拖着步子。有时候想找什么东西，明明就在眼前却半天反应不过来。跟邻居打招呼也要想好久才想起对方名字，记性越来越差了。",
    "医生：我明白这种反应变慢和记忆力下降的感受。您提到这些状况已经持续三个月了，这段时间里您觉得对日常生活的整体影响有多大？比如自理能力和社交方面。",
    "患者：现在连做饭都成问题，经常忘记关火，女儿给我买了电磁炉让我用。社区组织的活动都推掉了，连楼下散步都懒得去。最难受的是有时候想给外孙讲故事，却连最简单的成语都想不起来，心里特别难受。",
    "医生：您能坚持照顾自己已经很不容易了。我想了解一下，您刚才提到的那些消极念头，最近出现的频率如何？是每天都会出现，还是偶尔才会想到？",
    "患者：大概两三天就会想一次，特别是半夜醒来睡不着的时候。看到别人家老两口一起散步，或者听到邻居家的欢笑声，就会觉得特别孤单。但想到女儿和外孙，又会告诉自己得坚持下去。",
    "医生：感谢您如此坦诚地分享这些细节。为了能更好地帮助您，我想确认一下：除了已经提到的症状，您是否还有其他不适的感觉？比如过度自责，或者觉得自己没有价值之类的想法？",
    "患者：经常觉得自己很没用，教书教了一辈子，现在连简单的字都写不好。女儿给我买的新衣服都舍不得穿，总觉得像我这样没用的老太婆不配穿这么好的衣服。有时候还会想，要是当初多注意身体，现在也不会这样拖累孩子。",
    "医生：我理解这种自责的情绪会给您带来很大负担。您刚才提到半夜醒来时会陷入这些想法，通常需要多长时间才能重新入睡？这段时间会持续很久吗？",
    "患者：醒来后基本就睡不着了，眼睁睁等到天亮。有时候会坐在老伴的遗像前说说话，一说就是一两个小时。天亮后反而会困，但又怕睡太多晚上更睡不着，就这么硬撑着。",
    "医生：您能主动采取这些方式来缓解情绪已经很不容易了。在我们结束今天的谈话前，我想确认最后一个问题：您是否曾经有过任何伤害自己的念头或计划？即使只是短暂的想法也没关系。",
    "患者：从来没有过具体的计划。虽然有时候会觉得活着太累，但想到女儿会伤心，外孙还需要外婆，我就告诉自己必须好好活着。再难也要坚持吃药吃饭，不能让孩子们担心。",
    "医生：感谢您坦诚地告诉我这些。您对家人的爱和责任感令人感动，这份坚持的勇气也非常可贵。我建议我们下周再次见面，进一步讨论如何改善睡眠质量和调整负面思维模式。在这期间，如果您感到特别难受，可以随时联系我或拨打心理援助热线。今天您分享的每一个细节都非常有价值。",
    "患者：谢谢医生。和您说了这么多，心里好像轻松了一点。我会按时吃药的，也会试着每天出门走走。下周见。",
    "医生：很高兴听到您感觉轻松了一些。您已经迈出了很重要的一步，请记住您不是独自面对这些困难。下周见面时我们可以详细讨论适合您的日常活动安排，期待看到您的进展。保重。"
  ],
  "timestamp": "2025-10-09T21:36:54.552027"
}