{
  "case_id": 37,
  "is_depression": true,
  "disease_info": {
    "depression_level": "中度",
    "suicide_risk": 1,
    "symptoms_summary": ""
  },
  "case_info": {
    "basic_info": "34岁男性，某公司销售经理",
    "background": "因连续3个季度业绩不达标被降薪30%，每月需偿还房贷8000元，妻子无业，家庭经济压力骤增。"
  },
  "dialogue_history": [
    "医生：您好，我是您的AI医生。感谢您今天来就诊。作为一位职场人士，工作压力和经济负担可能会带来不小的挑战。能和我聊聊您最近的整体状态吗？",
    "患者：医生您好。最近确实压力很大，公司连续三个季度业绩不达标，我被降薪了30%。现在每个月还要还八千块的房贷，妻子又没有工作，每天醒来就觉得喘不过气，经常坐在车里发呆不想上楼。",
    "医生：我能感受到您肩上的重担和压力。这种喘不过气的感觉大概持续多久了呢？每天都会出现吗？",
    "患者：从降薪通知下来到现在快两个月了。特别是每天开车回家快到小区的时候，胸口就发闷，得在车里坐好久才能调整好状态上楼。白天见客户的时候能暂时忘记这些，但一个人独处时特别难受。",
    "医生：听起来您在工作中能够暂时分散注意力，这很不容易。除了情绪上的压力，您最近在睡眠和饮食方面有什么变化吗？",
    "患者：睡眠变得特别差，经常凌晨三四点就醒了，然后就再也睡不着。吃饭也没什么胃口，妻子说我最近瘦了不少，皮带都多扣了一个孔。有时候明明饿了，但看到饭菜就是不想动筷子。",
    "医生：我注意到您提到睡眠质量下降和食欲减退的情况。那么您平时喜欢的活动，比如和朋友聚会或者业余爱好，现在还愿意去做吗？",
    "患者：以前周末还经常和同事打打球，现在完全提不起劲。上周朋友约我去钓鱼，我找借口推掉了。就连看电视都觉得没意思，经常开着电视却坐在沙发上发呆，妻子说我最近反应都变慢了。",
    "医生：我理解这种对事物失去兴趣的感受。当您一个人发呆时，会不会经常感到疲惫或精力不足？即使没有做什么特别消耗体力的事情。",
    "患者：是的，明明没做什么却总觉得特别累。上周去见客户，连最简单的产品介绍都说得磕磕巴巴，脑子像生锈了一样。回到家连换衣服的力气都没有，就直接瘫在沙发上了。",
    "医生：这种精力不足和注意力难以集中的情况确实会让人感到困扰。您刚才提到对未来的担忧，是否曾经出现过一些消极的想法，比如觉得活着特别累之类的？",
    "患者：有时候晚上睡不着，会想如果一直这样下去该怎么办。看着妻子为我担心的样子，觉得自己特别失败，连家都养不好。但这种想法也就是一闪而过，毕竟还得继续工作还房贷。",
    "医生：感谢您愿意和我分享这些。当这些念头出现时，您通常会怎么应对呢？会主动和妻子聊聊您的感受吗？",
    "患者：不会跟她说太多，怕她更担心。每次她问起工作的事，我都说还行。其实经常一个人躲在书房抽烟，有时候一根接一根地抽，好像这样能稍微好受点。",
    "医生：抱歉，我暂时无法回应。",
    "患者：我知道这样不好，但就是控制不住。上周在高速上开车的时候，突然冒出一个念头觉得要是出个意外就好了，但马上就被自己吓到了，赶紧把车停到应急车道缓了好久。",
    "医生：我理解这种即使得到支持仍感到无力的心情。除了心理上的变化，您有没有注意到身体方面的一些改变？比如动作变得比平时慢，或者反而更坐立不安？",
    "患者：确实感觉整个人都变慢了。上周开会时领导问我话，我反应了好久才回答上来。平时走路也拖拖拉拉的，妻子说我最近连说话都慢吞吞的，经常说着说着就走神了。",
    "医生：我明白这种明明有任务却无法集中精力的感受。您提到这些状况已经持续两个月了，这段时间里您觉得对日常生活的整体影响有多大？比如工作和家庭生活方面。",
    "患者：工作影响很大，这个月又没完成业绩指标。回家后也不想说话，妻子做的饭经常剩很多。最糟糕的是明明知道该去跑客户，但就是提不起劲出门，经常在办公室一坐就是一整天却什么都没做成。",
    "医生：您能在这样的情况下仍然坚持工作，这显示出您仍在努力应对当前的困境。我想了解一下，您刚才提到的那些消极念头，最近出现的频率如何？是每天都会出现，还是偶尔才会想到？",
    "患者：大概每周会出现两三次吧。特别是看到同事开单或者收到还款提醒短信的时候，就会觉得特别绝望。但这些念头不会持续太久，毕竟还得继续工作养家。",
    "医生：感谢您如此坦诚地分享这些细节。为了能更好地帮助您，我想确认一下：除了已经提到的症状，您是否还有其他不适的感觉？比如过度自责，或者觉得自己没有价值之类的想法？",
    "患者：经常觉得自己很没用，同样的市场环境，别人都能完成业绩，就我不行。晚上睡不着的时候就会想，妻子嫁给我真是受苦了，连基本的生活都给不了她安稳。有时候甚至会想，要是没有我，她可能还能找个更好的人。",
    "医生：我理解这种自责的情绪会给您带来很大负担。您刚才提到晚上睡不着时会陷入这些想法，通常需要多长时间才能重新入睡？这段时间会持续很久吗？",
    "患者：醒来后基本就睡不着了，经常睁眼到天亮。有时候会爬起来看工作报表，但根本看不进去，就在书房一根接一根地抽烟。等到天快亮了才迷迷糊糊睡一会儿，然后又要赶着去上班。",
    "医生：您能坚持每天上班，这很不容易。在我们结束今天的谈话前，我想确认最后一个问题：您是否曾经有过任何伤害自己的念头或计划？即使只是短暂的想法也没关系。",
    "患者：从来没有具体计划过，就是偶尔会觉得太累了。但想到妻子和房贷，我知道必须坚持下去。最多就是在车里多坐一会儿，抽几根烟平复心情。",
    "医生：感谢您坦诚地告诉我这些。您对家庭的责任感和坚持的勇气令人敬佩。我建议我们下周再次见面，进一步讨论如何改善睡眠质量和调整负面思维模式。在这期间，如果您感到情绪特别低落，可以随时联系我或拨打心理援助热线。今天您分享的每一个细节都非常有价值。"
  ],
  "timestamp": "2025-10-09T21:16:18.859233"
}